_ceed_cffi.abi3.so
libceed/ceed_vector.py
libceed/ceed_qfunction.py
libceed/ceed.py
libceed/ceed_elemrestriction.py
libceed/build_ceed_cffi.py
libceed/__init__.py
libceed/ceed_constants.py
libceed/ceed_operator.py
libceed/ceed_qfunctioncontext.py
libceed/ceed_basis.py
libceed/lib/libceed.so
libceed/lib/pkgconfig/ceed.pc
libceed/include/ceed.h
libceed/include/ceedf.h
libceed/include/ceed/ceed-f32.h
libceed/include/ceed/ceed.h
libceed/include/ceed/backend.h
libceed/include/ceed/ceed-f64.h
libceed/include/ceed/hip.h
libceed/include/ceed/fortran.h
libceed/include/ceed/cuda.h
libceed/include/ceed/types.h
libceed/include/ceed/jit-source/gallery/ceed-scale.h
libceed/include/ceed/jit-source/gallery/ceed-vectorpoisson3dapply.h
libceed/include/ceed/jit-source/gallery/ceed-mass3dbuild.h
libceed/include/ceed/jit-source/gallery/ceed-identity.h
libceed/include/ceed/jit-source/gallery/ceed-massapply.h
libceed/include/ceed/jit-source/gallery/ceed-poisson1dapply.h
libceed/include/ceed/jit-source/gallery/ceed-poisson2dbuild.h
libceed/include/ceed/jit-source/gallery/ceed-mass1dbuild.h
libceed/include/ceed/jit-source/gallery/ceed-vectorpoisson1dapply.h
libceed/include/ceed/jit-source/gallery/ceed-poisson2dapply.h
libceed/include/ceed/jit-source/gallery/ceed-mass2dbuild.h
libceed/include/ceed/jit-source/gallery/ceed-poisson3dbuild.h
libceed/include/ceed/jit-source/gallery/ceed-poisson1dbuild.h
libceed/include/ceed/jit-source/gallery/ceed-vectorpoisson2dapply.h
libceed/include/ceed/jit-source/gallery/ceed-vectormassapply.h
libceed/include/ceed/jit-source/gallery/ceed-poisson3dapply.h
libceed/include/ceed/jit-source/magma/magma-basis-grad-nontensor.h
libceed/include/ceed/jit-source/magma/magma-basis-interp-2d.h
libceed/include/ceed/jit-source/magma/magma-basis-weight-1d.h
libceed/include/ceed/jit-source/magma/magma-basis-interp-3d.h
libceed/include/ceed/jit-source/magma/magma-basis-grad-2d.h
libceed-0.12.0.dist-info/METADATA
libceed-0.12.0.dist-info/LICENSE
libceed-0.12.0.dist-info/WHEEL
libceed-0.12.0.dist-info/RECORD
libceed-0.12.0.dist-info/top_level.txt
