Metadata-Version: 2.1
Name: libceed
Version: 0.12.0
Summary: libCEED: Code for Efficient Extensible Discretization
Home-page: https://libceed.org
Download-URL: https://github.com/CEED/libCEED/releases
Author: libCEED Team
Author-email: ceed-users@llnl.gov
License: BSD 2
Project-URL: Bug Tracker, https://github.com/CEED/libCEED/issues
Project-URL: Documentation, https://libceed.org
Project-URL: Source Code, https://github.com/CEED/libCEED
Keywords: libCEED
Platform: POSIX
Classifier: Development Status :: 4 - Beta
Classifier: Intended Audience :: Developers
Classifier: Intended Audience :: Science/Research
Classifier: License :: OSI Approved :: BSD License
Classifier: Operating System :: POSIX
Classifier: Programming Language :: C
Classifier: Programming Language :: C++
Classifier: Programming Language :: Fortran
Classifier: Programming Language :: Python
Classifier: Programming Language :: Python :: 3.5
Classifier: Programming Language :: Python :: 3.6
Classifier: Programming Language :: Python :: 3.7
Classifier: Programming Language :: Python :: 3.8
Classifier: Programming Language :: Python :: 3 :: Only
Classifier: Topic :: Scientific/Engineering
Classifier: Topic :: Software Development :: Libraries
License-File: LICENSE
Requires-Dist: cffi
Requires-Dist: numpy
Provides-Extra: cuda
Requires-Dist: numba; extra == "cuda"
